{
"type": "FeatureCollection",
"name": "LK29",
"crs": { "type": "name", "properties": { "name": "urn:ogc:def:crs:OGC:1.3:CRS84" } },
"features": [
{ "type": "Feature", "properties": { "Name": "PKP Lucynów", "description": "<br><div style=\"font-family:arial;font-size:10pt\">\n\n<u><b>Podstawowe informacje:<\/b><\/u>\n\n<ul>\n\n<li><b>przystanek kolejowy do modernizacji<\/b><\/li>\n\n<\/ul>\n\n<\/div>", "tessellate": "-1", "extrude": "0", "visibility": "0", "snippet": "" }, "geometry": { "type": "Point", "coordinates": [ 21.458975, 52.552764, 0.0 ] } },
{ "type": "Feature", "properties": { "Name": "PKP Rybienko", "description": "<br><div style=\"font-family:arial;font-size:10pt\">\n\n<u><b>Podstawowe informacje:<\/b><\/u>\n\n<ul>\n\n<li><b>przystanek kolejowy do modernizacji<\/b><\/li>\n\n<\/ul>\n\n<\/div>", "tessellate": "-1", "extrude": "0", "visibility": "0", "snippet": "" }, "geometry": { "type": "Point", "coordinates": [ 21.458401, 52.582053, 0.0 ] } },
{ "type": "Feature", "properties": { "Name": "PKP Wyszków", "description": "<br><div style=\"font-family:arial;font-size:10pt\">\n\n<u><b>Podstawowe informacje:<\/b><\/u>\n\n<ul>\n\n<li><b>przystanek kolejowy do modernizacji<\/b><\/li>\n\n<\/ul>\n\n<\/div>", "tessellate": "-1", "extrude": "0", "visibility": "0", "snippet": "" }, "geometry": { "type": "Point", "coordinates": [ 21.446535, 52.601824, 0.0 ] } }
]
}
